odoo/addons/l10n_fr_oca/README.rst
odoo/addons/l10n_fr_oca/__init__.py
odoo/addons/l10n_fr_oca/__manifest__.py
odoo/addons/l10n_fr_oca/data/account.account.template.csv
odoo/addons/l10n_fr_oca/data/account.group.template.csv
odoo/addons/l10n_fr_oca/data/account_account_template_default_tax.xml
odoo/addons/l10n_fr_oca/data/account_chart_template_configure_data.xml
odoo/addons/l10n_fr_oca/data/account_chart_template_data.xml
odoo/addons/l10n_fr_oca/data/account_fiscal_position_template_data.xml
odoo/addons/l10n_fr_oca/data/account_reconcile_model_template.xml
odoo/addons/l10n_fr_oca/data/account_tax_data.xml
odoo/addons/l10n_fr_oca/data/l10n_fr_chart_data.xml
odoo/addons/l10n_fr_oca/data/tax_report_data.xml
odoo/addons/l10n_fr_oca/demo/demo_company.xml
odoo/addons/l10n_fr_oca/i18n/l10n_fr_oca.pot
odoo/addons/l10n_fr_oca/readme/CONTRIBUTORS.rst
odoo/addons/l10n_fr_oca/readme/DESCRIPTION.rst
odoo/addons/l10n_fr_oca/static/description/icon.png
odoo/addons/l10n_fr_oca/static/description/index.html
odoo14_addon_l10n_fr_oca-14.0.2.0.0.dist-info/METADATA
odoo14_addon_l10n_fr_oca-14.0.2.0.0.dist-info/WHEEL
odoo14_addon_l10n_fr_oca-14.0.2.0.0.dist-info/top_level.txt
odoo14_addon_l10n_fr_oca-14.0.2.0.0.dist-info/RECORD
