Metadata-Version: 2.1
Name: odoo14-addon-l10n_fr_oca
Version: 14.0.2.0.0
Summary: Fork of l10n_fr: fewer taxes, ready for OCA VAT return for France
Home-page: https://github.com/OCA/l10n-france
Author: Akretion,Odoo SA,Odoo Community Association (OCA)
Author-email: support@odoo-community.org
License: LGPL-3
Classifier: Programming Language :: Python
Classifier: Framework :: Odoo
Classifier: Framework :: Odoo :: 14.0
Classifier: License :: OSI Approved :: GNU Lesser General Public License v3 (LGPLv3)
Requires-Python: >=3.6
Requires-Dist: odoo14-addon-account-tax-unece
Requires-Dist: odoo <14.1dev,>=14.0a
